{
  "hash": "9ed99b95",
  "configHash": "f30723ca",
  "lockfileHash": "8c90f0eb",
  "browserHash": "982f16ec",
  "optimized": {
    "react/jsx-dev-runtime": {
      "src": "../../node_modules/react/jsx-dev-runtime.js",
      "file": "react_jsx-dev-runtime.js",
      "fileHash": "9f026816",
      "needsInterop": true
    },
    "react": {
      "src": "../../node_modules/react/index.js",
      "file": "react.js",
      "fileHash": "47483326",
      "needsInterop": true
    },
    "react-dom/client": {
      "src": "../../node_modules/react-dom/client.js",
      "file": "react-dom_client.js",
      "fileHash": "23c9acb9",
      "needsInterop": true
    },
    "@mui/material/styles": {
      "src": "../../node_modules/@mui/material/styles/index.js",
      "file": "@mui_material_styles.js",
      "fileHash": "5bbe6b3f",
      "needsInterop": false
    },
    "clsx": {
      "src": "../../node_modules/clsx/dist/clsx.mjs",
      "file": "clsx.js",
      "fileHash": "ae193c49",
      "needsInterop": false
    },
    "@mui/material": {
      "src": "../../node_modules/@mui/material/index.js",
      "file": "@mui_material.js",
      "fileHash": "9665c0fe",
      "needsInterop": false
    }
  },
  "chunks": {
    "chunk-JMVEG3FK": {
      "file": "chunk-JMVEG3FK.js"
    },
    "chunk-KJGA4PLF": {
      "file": "chunk-KJGA4PLF.js"
    },
    "chunk-TWJRYSII": {
      "file": "chunk-TWJRYSII.js"
    },
    "chunk-KDVGFZWC": {
      "file": "chunk-KDVGFZWC.js"
    },
    "chunk-DC5AMYBS": {
      "file": "chunk-DC5AMYBS.js"
    }
  }
}